counter_example/first_counter.v
// -------Counter design specs--------
// 4 bit synchronous up counter
// Active high enable

module first_counter (
    clock, // Clock input design
    reset, // Active high, synchronous reset input
    enable, // Active high Enable signal for counter
    counter_out // 4 bit vector output of the counter
); // End of port list
//Input ports
input clock;
input reset;
input enable;
//Output ports
output [3:0] counter_out;
//Input port datatypes
//By rule all input port should be wires
wire clock;
wire reset;
wire enable;
//Output port datatype
// Output port can be storage elements or wires
reg [3:0] counter_out;

//Code start
//Since the counter is edge trigger one 
//We trigger the below block with respective positive edge of the clock
always @(posedge clock)
begin: COUNTER //Block name
// At every rising edge of the clock we check if the reset is active
// if active; we load the counter with 4'b0000
if (reset==1'b1) begin
    counter_out <= #1 4'b0000;
    end
else if (enable==1'b1) begin
    counter_out <= counter_out+1;
    end
end
endmodule

counter_example/first_counter_tb.v
`include "first_counter.v"

module first_counter_tb();
//Declare inputs as reg and outputs as wires
reg clock;
reg enable;
reg reset;
wire [3:0] counter_out;
//Initialize all variables
initial begin
    $dumpfile("first_counter_tb.vcd");
    $dumpvars(0, first_counter_tb);
    $display("time\t clk reset enable counter");
    $monitor("%g\t %b   %b     %b      %b", $time, clock, reset, enable, counter_out);
    clock = 1; //initial value of the clock
    reset = 0; //initial value of the reset
    enable = 0; //initial value of the enable
    #5 reset = 1; //Assert the reset
    #10 reset = 0; //De assert the reset
    #10 enable = 1; //Assert the enable
    #100 enable = 0; //De-assert the enable
    #5 $finish; //Terminate simulation
end
//Clock generator
always begin
    #5 clock = ~clock; //Toggle every 5 clicks
end

// Connect DUT(Device under test) to test_bench
first_counter U_counter(clock,reset,enable, counter_out);
endmodule

counter_example/first_counter_tb.vcd
$date
	Sat Sep  9 14:52:37 2023
$end
$version
	Icarus Verilog
$end
$timescale
	1s
$end
$scope module first_counter_tb $end
$var wire 4 ! counter_out [3:0] $end
$var reg 1 " clock $end
$var reg 1 # enable $end
$var reg 1 $ reset $end
$scope module U_counter $end
$var wire 1 " clock $end
$var wire 1 # enable $end
$var wire 1 $ reset $end
$var reg 4 % counter_out [3:0] $end
$scope begin COUNTER $end
$upscope $end
$upscope $end
$upscope $end
$enddefinitions $end
$comment Show the parameter values. $end
$dumpall
$end
#0
$dumpvars
bx %
0$
0#
1"
bx !
$end
#5
0"
1$
#10
1"
#11
b0 !
b0 %
#15
0"
0$
#20
1"
#25
0"
1#
#30
b1 !
b1 %
1"
#35
0"
#40
b10 !
b10 %
1"
#45
0"
#50
b11 !
b11 %
1"
#55
0"
#60
b100 !
b100 %
1"
#65
0"
#70
b101 !
b101 %
1"
#75
0"
#80
b110 !
b110 %
1"
#85
0"
#90
b111 !
b111 %
1"
#95
0"
#100
b1000 !
b1000 %
1"
#105
0"
#110
b1001 !
b1001 %
1"
#115
0"
#120
b1010 !
b1010 %
1"
#125
0"
0#
