flipflop/d_flipflop.v
//filename:- d_flipflop.v
module d_flipflop_1bit(
data,
clk,
reset,
set,
Q,
Q_bar
);
//declare inputs
input data;
input clk;
input reset;
input set;
//Declare outputs
output Q;
output Q_bar;
//declare port datatypes
wire data;
wire clk;
wire reset;
wire set;
reg Q;
//logic
assign Q_bar = ~Q;
always @(posedge clk) begin
    if (reset==1'b1) begin
        Q<=0; //set dff to 0
    end
    else if (set==1'b1) begin
        Q <= 1; //set dff to 1
    end
    else begin
        Q<=data;
    end
end
endmodule

flipflop/d_flipflop_testbench.v
//filename:- d_filflop_testbench.v
`include "d_flipflop.v"

module d_flipflop_testbench;
//input ports
reg data;
reg clk;
reg reset;
reg set;
//output ports
wire Q;
wire Q_bar;

//initial block
initial begin
    clk = 0; //start value for clock
    data = 0; // start value for data
    reset = 0; // start value for reset
    set = 0; // start value for reset
    $dumpfile("d_flipflop_testbench.vcd");
    $dumpvars(0, d_flipflop_testbench);
    $display("time\t clk   set   reset   data     Q    Q_bar");
    $monitor("%g\t %b\t %b\t %b\t %b\t %b\t %b ",$time,clk,set,reset,data,Q,Q_bar);
    #10data = 1'b1;
    #10set = 1'b0;
    #10set =  1'b1;
    #10reset = 1'b0;
    #10reset = 1'b1;
    #10data= 1'b0;
    #5data=1'b1;
    #5data=1'b0;
    #5data=1'b1;
    #5data=1'b0;
    $finish;
end

always begin
    #5clk = ~clk; // toggle clock every 5 unit time 
end

// call "d_flipflop_1bit" module to run the test bech
d_flipflop_1bit uut(
    .data(data),
    .clk(clk),
    .reset(reset),
    .set(set),
    .Q(Q),
    .Q_bar(Q_bar)
);
endmodule

flipflop/d_flipflop_testbench.vcd
$date
	Mon Sep 11 17:48:09 2023
$end
$version
	Icarus Verilog
$end
$timescale
	1s
$end
$scope module d_flipflop_testbench $end
$var wire 1 ! Q_bar $end
$var wire 1 " Q $end
$var reg 1 # clk $end
$var reg 1 $ data $end
$var reg 1 % reset $end
$var reg 1 & set $end
$scope module uut $end
$var wire 1 ! Q_bar $end
$var wire 1 # clk $end
$var wire 1 $ data $end
$var wire 1 % reset $end
$var wire 1 & set $end
$var reg 1 " Q $end
$upscope $end
$upscope $end
$enddefinitions $end
$comment Show the parameter values. $end
$dumpall
$end
#0
$dumpvars
0&
0%
0$
0#
x"
x!
$end
#5
1!
0"
1#
#10
0#
1$
#15
0!
1"
1#
#20
0#
#25
1#
#30
0#
1&
#35
1#
#40
0#
#45
1#
#50
0#
1%
#55
1!
0"
1#
#60
0#
0$
#65
1#
1$
#70
0#
0$
#75
1#
1$
#80
0#
0$
