mux/mux_16x1.v
module mux_4x1(
    data_in,
    select,
    data_out
);
//declare inputs and outputs
input [3:0] data_in; //4 bit
input [1:0] select; // 2 bit
output data_out;
//declare port datatype
wire [3:0] data_in;
wire [1:0] select;
wire data_out;
//logic
assign data_out = (select==2'b00)?data_in[0]:(select==2'b01)?data_in[1]:(select==2'b10)?data_in[2]:data_in[3];
endmodule

module mux_16x1(
    data_in,
    select,
    data_out
);
//declare inputs and outputs
input [15:0] data_in;
input [3:0] select;
output data_out;
//declare portdata type
wire [15:0] data_in;
wire [3:0] select;
wire data_out;
//extra wires for intermediate connections
wire [3:0] data_out_intermediate;
//logic using mux_4x1 module
//mux-1 to select using select[0:1] for data_in[0:3] 
mux_4x1 u0(
    .data_in(data_in[3:0]),
    .select(select[1:0]),
    .data_out(data_out_intermediate[0])
);
//mux-2 to select using select[0:1] for data_in[4:7] 
mux_4x1 u1(
    .data_in(data_in[7:4]),
    .select(select[1:0]),
    .data_out(data_out_intermediate[1])
);
//mux-3 to select using select[0:1] for data_in[8:11] 
mux_4x1 u2(
    .data_in(data_in[11:8]),
    .select(select[1:0]),
    .data_out(data_out_intermediate[2])
);
//mux to select using select[0:1] for data_in[12:15] 
mux_4x1 u3(
    .data_in(data_in[15:12]),
    .select(select[1:0]),
    .data_out(data_out_intermediate[3])
);
//mux to select using select[2:3] for {data_in_3, data_in_2, data_in_1, data_in_0} 
mux_4x1 u4(
    .data_in(data_out_intermediate),
    .select(select[3:2]),
    .data_out(data_out)
);
endmodule

mux/mux_16x1_testbench.v
`include "mux_16x1.v"

module mux_16x1_testbench;
//inputs and outputs
reg [15:0] data_in;
reg [3:0] select;
wire data_out;

initial begin
    //initialize inputs
    data_in=16'b0000000000000000;
    select=4'b0000;
    //save to vcd file
    $dumpfile("mux_16x1_testbench.vcd");
    $dumpvars(0, mux_16x1_testbench);
    $display("data_in\t\tselect\tdata_out");
    $monitor("%b %b    %b",data_in, select, data_out);
    //test case
    data_in=16'b0000100111101110;
    select=4'b0000;
    #10data_in=16'b1111111100111110;
    select=4'b0001;
    #10data_in=16'b0000001001011000;
    select=4'b0010;
    #10data_in=16'b0110010010110100;
    select=4'b0011;
    #10data_in=16'b0000000001000000;
    select=4'b0100;
    #10data_in=16'b0011110110000001;
    select=4'b1000;
    #10data_in=16'b0000101101010000;
    select=4'b0101;
    #10data_in=16'b1100000000000000;
    select=4'b1111;
    #10$finish;
end
//instantiate mux_16x1 module
mux_16x1 uut(
    .data_in(data_in),
    .select(select),
    .data_out(data_out)
);
endmodule

mux/mux_16x1_testbench.vcd
$date
	Mon Sep 11 20:12:33 2023
$end
$version
	Icarus Verilog
$end
$timescale
	1s
$end
$scope module mux_16x1_testbench $end
$var wire 1 ! data_out $end
$var reg 16 " data_in [15:0] $end
$var reg 4 # select [3:0] $end
$scope module uut $end
$var wire 16 $ data_in [15:0] $end
$var wire 4 % select [3:0] $end
$var wire 4 & data_out_intermediate [3:0] $end
$var wire 1 ! data_out $end
$scope module u0 $end
$var wire 4 ' data_in [3:0] $end
$var wire 2 ( select [1:0] $end
$var wire 1 ) data_out $end
$upscope $end
$scope module u1 $end
$var wire 4 * data_in [3:0] $end
$var wire 2 + select [1:0] $end
$var wire 1 , data_out $end
$upscope $end
$scope module u2 $end
$var wire 4 - data_in [3:0] $end
$var wire 2 . select [1:0] $end
$var wire 1 / data_out $end
$upscope $end
$scope module u3 $end
$var wire 4 0 data_in [3:0] $end
$var wire 2 1 select [1:0] $end
$var wire 1 2 data_out $end
$upscope $end
$scope module u4 $end
$var wire 4 3 data_in [3:0] $end
$var wire 2 4 select [1:0] $end
$var wire 1 ! data_out $end
$upscope $end
$upscope $end
$upscope $end
$enddefinitions $end
$comment Show the parameter values. $end
$dumpall
$end
#0
$dumpvars
b0 4
b100 3
02
b0 1
b0 0
1/
b0 .
b1001 -
0,
b0 +
b1110 *
0)
b0 (
b1110 '
b100 &
b0 %
b100111101110 $
b0 #
b100111101110 "
0!
$end
#10
1!
1)
1,
b1111 &
b1111 3
12
b1 (
b1 +
b1 .
b1 1
b11 *
b1111 -
b1111 0
b1 #
b1 %
b1111111100111110 "
b1111111100111110 $
#20
0!
0)
0/
b10 &
b10 3
02
b10 (
b10 +
b10 .
b10 1
b1000 '
b101 *
b10 -
b0 0
b10 #
b10 %
b1001011000 "
b1001011000 $
#30
b11 (
b11 +
b11 .
b11 1
b100 '
b1011 *
b100 -
b110 0
b11 #
b11 %
b110010010110100 "
b110010010110100 $
#40
b0 &
b0 3
0,
0!
b0 (
b0 +
b0 .
b0 1
b1 4
b0 '
b100 *
b0 -
b0 0
b100 #
b100 %
b1000000 "
b1000000 $
#50
1!
1)
1/
b1101 &
b1101 3
12
b10 4
b1 '
b1000 *
b1101 -
b11 0
b1000 #
b1000 %
b11110110000001 "
b11110110000001 $
#60
0!
0)
b100 &
b100 3
02
b1 (
b1 +
b1 .
b1 1
b1 4
b0 '
b101 *
b1011 -
b0 0
b101 #
b101 %
b101101010000 "
b101101010000 $
#70
1!
0/
b1000 &
b1000 3
12
b11 (
b11 +
b11 .
b11 1
b11 4
b0 *
b0 -
b1100 0
b1111 #
b1111 %
b1100000000000000 "
b1100000000000000 $
