decoder/decoder3x8.v
// Filename:- decoder3x8.v
module decoder3x8(
    data_in,
    data_out,
    enable
);
//declare inputs
input [2:0] data_in;
input enable;
//decalre outputs
output [7:0] data_out;
//declare port datatypes
wire [2:0] data_in;
reg [7:0] data_out;
wire enable;
//always block for decoder logic
always @(data_in)
begin
    if (enable==1'b1) begin // if logic circuit receives enable signal = 1
        case (data_in) // data out based on case
        3'b000: data_out = 8'b00000001; // selecting data_out line 0
        3'b001: data_out = 8'b00000010; // selecting data_out line 1
        3'b010: data_out = 8'b00000100; // selecting data_out line 2
        3'b011: data_out = 8'b00001000; // selecting data_out line 3
        3'b100: data_out = 8'b00010000; // selecting data_out line 4
        3'b101: data_out = 8'b00100000; // selecting data_out line 5
        3'b110: data_out = 8'b01000000; // selecting data_out line 6
        3'b111: data_out = 8'b10000000; // selecting data_out line 7
        default : data_out = 8'b00000000;
        endcase
    end else begin
        data_out = 8'bxxxxxxxx;
    end

end
endmodule

decoder/decoder3x8_testbench.v
// Filename:- decoder3x8_testbench.v
`include "decoder3x8.v"

module decoder3x8_testbench;
// //inputs and outputs
// input [2:0] data_in;
// input enable;
// output [7:0] data_out;
//datatype declaration
reg [2:0] data_in;
reg enable;
wire [7:0] data_out;
//test bench variable initilisation 
initial begin
    $dumpfile("decoder3x8_testbench.vcd");
    $dumpvars(0, decoder3x8_testbench);
    $display("enable\t data_in\t data_out");
    $monitor("%b\t %b\t %b\t ", enable, data_in, data_out);
    data_in = 3'b001;
    #10data_in = 3'b010;
    #10data_in = 3'b011;
    #10data_in = 3'b000;
    #10data_in = 3'b001;
    #10data_in = 3'b010;
    #10data_in = 3'b011;
    #10data_in = 3'b100;
    #10data_in = 3'b101;
    #10data_in = 3'b110;
    #10data_in = 3'b111;
end
initial begin
    enable=1'b0;
    #30enable = 1'b1;
end

decoder3x8 uut(
    .enable(enable),
    .data_in(data_in),
    .data_out(data_out)
);
endmodule

decoder/decoder3x8_testbench.vcd
$date
	Mon Sep 11 13:41:57 2023
$end
$version
	Icarus Verilog
$end
$timescale
	1s
$end
$scope module decoder3x8_testbench $end
$var wire 8 ! data_out [7:0] $end
$var reg 3 " data_in [2:0] $end
$var reg 1 # enable $end
$scope module uut $end
$var wire 3 $ data_in [2:0] $end
$var wire 1 # enable $end
$var reg 8 % data_out [7:0] $end
$upscope $end
$upscope $end
$enddefinitions $end
$comment Show the parameter values. $end
$dumpall
$end
#0
$dumpvars
bx %
b1 $
0#
b1 "
bx !
$end
#10
b10 "
b10 $
#20
b11 "
b11 $
#30
b1 !
b1 %
b0 "
b0 $
1#
#40
b10 !
b10 %
b1 "
b1 $
#50
b100 !
b100 %
b10 "
b10 $
#60
b1000 !
b1000 %
b11 "
b11 $
#70
b10000 !
b10000 %
b100 "
b100 $
#80
b100000 !
b100000 %
b101 "
b101 $
#90
b1000000 !
b1000000 %
b110 "
b110 $
#100
b10000000 !
b10000000 %
b111 "
b111 $
